daemon/__init__.py
send_email/__init__.py
send_email/send_email_py2.py
utils/__init__.py
utils/async.py
utils/database.py
utils/decorator.py
utils/dict.py
utils/do.py
utils/expiringdict.py
utils/json_serialize.py
utils/log.py
utils/thread.py
utils/timeline.py
weaminglib-0.1.1.dist-info/METADATA
weaminglib-0.1.1.dist-info/RECORD
weaminglib-0.1.1.dist-info/WHEEL
weaminglib-0.1.1.dist-info/top_level.txt
