Metadata-Version: 2.1
Name: weaminglib
Version: 0.1.1
Summary: library for personal use
Home-page: https://gitlab.com/weaming/pylib
Author: weaming
Author-email: garden.yuen@gmail.com
License: UNKNOWN
Project-URL: Source, https://gitlab.com/weaming/pylib
Project-URL: Bug Reports, https://gitlab.com/weaming/pylib
Platform: UNKNOWN
